{
  "name": "Dodge Salve I",
  "type": "consumable",
  "img": "icons/svg/item-bag.svg",
  "data": {
    "description": "<p>The target gains a +1 bonus to [Evasion]. (CR14): This item has no effect.</p>",
    "timing": "minor",
    "check": {
      "type": "none",
      "caster": "accuracy",
      "bonus": "",
      "addsr": false,
      "target": "evasion"
    },
    "range": {
      "type": "",
      "value": "Close"
    },
    "target": {
      "type": "self",
      "value": "0",
      "addsr": false
    },
    "tags": "Medicine, Consumable, Rare, Preparation",
    "ir": 7,
    "quantity": 1,
    "size": 1,
    "price": 190
  },
  "effects": [],
  "folder": null,
  "sort": 0,
  "permission": {
    "default": 0
  },
  "flags": {},
  "_id": "HKnFJofQ6uOsie1Q",
  "_key": "!items!HKnFJofQ6uOsie1Q"
}